Metadata-Version: 2.1
Name: Serverside-tables-django-framework
Version: 0.0.2
Summary: Vista de procesamiento de tabla de datos del lado del servidor simple para Django-framework
Home-page: https://github.com/carlosvisbal/Serverside-tables-django-framework
Author: Carlos Visbal
Author-email: carlosvisbal66@gmail.com
License: MIT
Platform: UNKNOWN
Classifier: Programming Language :: Python :: 3
Classifier: License :: OSI Approved :: MIT License
Classifier: Operating System :: OS Independent
Requires-Python: >=3.6
